{
  "coc.preferences.formatOnSaveFiletypes": ["javascript", "typescript", "typescriptreact", "json", "javascriptreact", "typescript.tsx"],

  "eslint.filetypes": ["javascript", "typescript", "typescriptreact", "javascriptreact", "typescript.tsx"],
  "diagnostic.errorSign": "•",
  "diagnostic.warningSign": "•",
  "diagnostic.infoSign": "•",

  "prettier.printWidth": 100,
  "prettier.tabWidth": 2,
  "prettier.useTabs": false,
  "prettier.semi": true,
  "prettier.singleQuote": true,
  "prettier.bracketSpacing": true,
  "prettier.jsxBracketSameLine": true,
  "prettier.arrowParens": "always",
  "prettier.trailingComma": "es5",
  "prettier.parser": "flow",
  "prettier.proseWrap": "preserve",
  "prettier.htmlWhitespaceSensitivity": "css"
}
